fastecdsa/__init__.py
fastecdsa/_ecdsa.cp38-win32.pyd
fastecdsa/benchmark.py
fastecdsa/curve.py
fastecdsa/curvemath.cp38-win32.pyd
fastecdsa/ecdsa.py
fastecdsa/keys.py
fastecdsa/point.py
fastecdsa/util.py
fastecdsa/encoding/__init__.py
fastecdsa/encoding/asn1.py
fastecdsa/encoding/der.py
fastecdsa/encoding/pem.py
fastecdsa/encoding/sec1.py
fastecdsa/encoding/util.py
fastecdsa/tests/__init__.py
fastecdsa/tests/test_asn1.py
fastecdsa/tests/test_brainpool_ecdh.py
fastecdsa/tests/test_key_encoding.py
fastecdsa/tests/test_key_recovery.py
fastecdsa/tests/test_keygen.py
fastecdsa/tests/test_nonce_generation.py
fastecdsa/tests/test_p256_ecdsa.py
fastecdsa/tests/test_prime_field_curve_math.py
fastecdsa/tests/test_rfc6979_ecdsa.py
fastecdsa/tests/test_signature_encoding.py
fastecdsa/tests/test_whitespace_parsing.py
fastecdsa_any-1.7.5.dist-info/LICENSE
fastecdsa_any-1.7.5.dist-info/METADATA
fastecdsa_any-1.7.5.dist-info/WHEEL
fastecdsa_any-1.7.5.dist-info/top_level.txt
fastecdsa_any-1.7.5.dist-info/RECORD
