Metadata-Version: 2.1
Name: fastecdsa-any
Version: 1.7.5
Summary: Fast elliptic curve digital signatures - built windows wheels
Home-page: https://github.com/ShadowJonathan/fastecdsa-any
Author: Anton Kueltz
Author-email: kueltz.anton@gmail.com
License: CC0 1.0 Universal (CC0 1.0) Public Domain Dedication
Keywords: elliptic curve cryptography ecdsa ecc
Platform: UNKNOWN
Classifier: Development Status :: 4 - Beta
Classifier: Intended Audience :: Developers
Classifier: Topic :: Security :: Cryptography
Classifier: License :: CC0 1.0 Universal (CC0 1.0) Public Domain Dedication
Classifier: Programming Language :: Python :: 3.6
Classifier: Programming Language :: Python :: 3.7
Classifier: Programming Language :: Python :: 3.8
Classifier: Operating System :: MacOS :: MacOS X
Classifier: Operating System :: POSIX :: Linux
Requires-Dist: six
